ema_workbench/__init__.py
ema_workbench/analysis/__init__.py
ema_workbench/analysis/b_and_w_plotting.py
ema_workbench/analysis/cart.py
ema_workbench/analysis/clusterer.py
ema_workbench/analysis/dimensional_stacking.py
ema_workbench/analysis/feature_scoring.py
ema_workbench/analysis/logistic_regression.py
ema_workbench/analysis/pairs_plotting.py
ema_workbench/analysis/parcoords.py
ema_workbench/analysis/plotting.py
ema_workbench/analysis/plotting_util.py
ema_workbench/analysis/prim.py
ema_workbench/analysis/prim_util.py
ema_workbench/analysis/regional_sa.py
ema_workbench/analysis/scenario_discovery_util.py
ema_workbench/connectors/__init__.py
ema_workbench/connectors/excel.py
ema_workbench/connectors/netlogo.py
ema_workbench/connectors/pysd_connector.py
ema_workbench/connectors/simio_connector.py
ema_workbench/connectors/vadere.py
ema_workbench/connectors/vensim.py
ema_workbench/connectors/vensimDLLwrapper.py
ema_workbench/em_framework/__init__.py
ema_workbench/em_framework/callbacks.py
ema_workbench/em_framework/evaluators.py
ema_workbench/em_framework/experiment_runner.py
ema_workbench/em_framework/futures_ipyparallel.py
ema_workbench/em_framework/futures_mpi.py
ema_workbench/em_framework/futures_multiprocessing.py
ema_workbench/em_framework/futures_util.py
ema_workbench/em_framework/model.py
ema_workbench/em_framework/optimization.py
ema_workbench/em_framework/outcomes.py
ema_workbench/em_framework/outputspace_exploration.py
ema_workbench/em_framework/parameters.py
ema_workbench/em_framework/points.py
ema_workbench/em_framework/salib_samplers.py
ema_workbench/em_framework/samplers.py
ema_workbench/em_framework/util.py
ema_workbench/examples/__init__.py
ema_workbench/examples/example_eijgenraam.py
ema_workbench/examples/example_excel.py
ema_workbench/examples/example_flu.py
ema_workbench/examples/example_lake_model.py
ema_workbench/examples/example_mesa.py
ema_workbench/examples/example_mpi_lake_model.py
ema_workbench/examples/example_netlogo.py
ema_workbench-2.5.3.dist-info/licenses/LICENSE.md
ema_workbench-2.5.3.dist-info/METADATA
ema_workbench-2.5.3.dist-info/WHEEL
ema_workbench-2.5.3.dist-info/top_level.txt
ema_workbench-2.5.3.dist-info/RECORD
