Metadata-Version: 2.4
Name: ema_workbench
Version: 2.5.3
Summary: Exploratory modelling in Python
Author-email: Jan Kwakkel <j.h.kwakkel@tudelft.nl>
License: Copyright (c) 2010-2016, Delft University of Technology
Project-URL: Homepage, https://github.com/quaquel/EMAworkbench
Project-URL: Documentation, https://emaworkbench.readthedocs.io/
Project-URL: Bug Tracker, https://github.com/quaquel/EMAworkbench/issues
Classifier: Programming Language :: Python :: 3
Classifier: License :: OSI Approved :: BSD License
Classifier: Operating System :: OS Independent
Requires-Python: >=3.9
License-File: LICENSE.md
Requires-Dist: numpy
Requires-Dist: pandas
Requires-Dist: scikit-learn
Requires-Dist: salib>=1.4.6
Requires-Dist: platypus-opt
Requires-Dist: matplotlib
Requires-Dist: statsmodels
Requires-Dist: seaborn
Requires-Dist: tqdm
Provides-Extra: recommended
Requires-Dist: ema_workbench[dev,graph,jupyter]; extra == "recommended"
Provides-Extra: all
Requires-Dist: ema_workbench[cov,dev,docs,graph,jupyter,parallel]; extra == "all"
Provides-Extra: jupyter
Requires-Dist: jupyter; extra == "jupyter"
Requires-Dist: jupyter_client; extra == "jupyter"
Requires-Dist: ipython; extra == "jupyter"
Requires-Dist: ipykernel; extra == "jupyter"
Provides-Extra: dev
Requires-Dist: pytest; extra == "dev"
Requires-Dist: pytest-mock; extra == "dev"
Requires-Dist: jupyter_client; extra == "dev"
Requires-Dist: ipyparallel; extra == "dev"
Provides-Extra: cov
Requires-Dist: pytest-cov; extra == "cov"
Requires-Dist: coverage; extra == "cov"
Requires-Dist: coveralls; extra == "cov"
Provides-Extra: docs
Requires-Dist: sphinx; extra == "docs"
Requires-Dist: sphinx-rtd-theme; extra == "docs"
Requires-Dist: readthedocs-sphinx-search; extra == "docs"
Requires-Dist: nbsphinx; extra == "docs"
Requires-Dist: myst; extra == "docs"
Requires-Dist: pyscaffold; extra == "docs"
Requires-Dist: myst-parser; extra == "docs"
Provides-Extra: graph
Requires-Dist: altair; extra == "graph"
Requires-Dist: pydot; extra == "graph"
Requires-Dist: graphviz; extra == "graph"
Provides-Extra: parallel
Requires-Dist: ipyparallel; extra == "parallel"
Requires-Dist: traitlets; extra == "parallel"
Provides-Extra: netlogo
Requires-Dist: jpype-1; extra == "netlogo"
Requires-Dist: pynetlogo; extra == "netlogo"
Provides-Extra: pysd
Requires-Dist: pysd; extra == "pysd"
Provides-Extra: simio
Requires-Dist: pythonnet; extra == "simio"
Dynamic: license-file
